{
  "updated_at": "2026-04-26T09:06:31.346086+10:00",
  "stats": {
    "News Items": "8",
    "Brisbane Temp": "19.0°C",
    "AUD/USD": "0.714697",
    "Errors": "0"
  },
  "stats_zh": {
    "新闻数量": "8",
    "布里斯班温度": "19.0°C",
    "澳元/美元": "0.714697",
    "异常数": "0"
  },
  "stats_en": {
    "News Items": "8",
    "Brisbane Temp": "19.0°C",
    "AUD/USD": "0.714697",
    "Errors": "0"
  },
  "summary": [
    "监控时间: 2026-04-26 09:06:31 AEST",
    "新闻抓取数量: 8",
    "布里斯班温度: 19.0°C",
    "AUD/USD: 0.714697"
  ],
  "summary_zh": [
    "监控时间: 2026-04-26 09:06:31 AEST",
    "新闻抓取数量: 8",
    "布里斯班温度: 19.0°C",
    "AUD/USD: 0.714697"
  ],
  "summary_en": [
    "Monitor Time: 2026-04-26 09:06:31 AEST",
    "News Items: 8",
    "Brisbane Temp: 19.0°C",
    "AUD/USD: 0.714697"
  ],
  "events": [
    {
      "title": "Brisbane Weather",
      "title_en": "Brisbane Weather",
      "title_zh": "布里斯班天气",
      "description": "Temperature 19.0°C, Wind 9.5km/h",
      "description_en": "Temperature 19.0°C, Wind 9.5km/h",
      "description_zh": "温度 19.0°C，风速 9.5km/h",
      "time": "2026-04-26 09:00",
      "type": "weather",
      "url": ""
    },
    {
      "title": "AUD/USD",
      "title_en": "AUD/USD",
      "title_zh": "澳元/美元",
      "description": "1 AUD = 0.714697 USD",
      "description_en": "1 AUD = 0.714697 USD",
      "description_zh": "1 澳元 = 0.714697 美元",
      "time": "Sat, 25 Apr 2026 00:02:32 +0000",
      "type": "market",
      "url": "https://open.er-api.com/"
    },
    {
      "title": "Shaun Micallef would hate to be immortal, so he wrote a vampire novel",
      "url": "https://www.abc.net.au/news/2026-04-26/shaun-micallef-death-takes-a-holiday-vampire-novel/106594994",
      "description": "After Shaun Micallef finished up 11 years hosting comedy news show Mad as Hell in 2022, the comedian did something unexpected: he wrote a 'gothic romance novel'.",
      "time": "2026-04-26 09:00",
      "type": "news",
      "title_en": "Shaun Micallef would hate to be immortal, so he wrote a vampire novel",
      "title_zh": "肖恩·米卡勒夫不想永生，所以他写了一本吸血鬼小说",
      "description_en": "After Shaun Micallef finished up 11 years hosting comedy news show Mad as Hell in 2022, the comedian did something unexpected: he wrote a 'gothic romance novel'.",
      "description_zh": "肖恩·米卡莱夫 (Shaun Micallef) 于 2022 年结束了 11 年的喜剧新闻节目《疯狂地狱》的主持后，这位喜剧演员做了一件意想不到的事情：他写了一本“哥特式浪漫小说”。"
    },
    {
      "title": "FOI documents show vetting process for NT's controversial Crown representative",
      "url": "https://www.abc.net.au/news/2026-04-26/nt-administrator-david-connolly-social-media-due-diligence/106585072",
      "description": "Months before a furore over his social media posts, documents show the federal government completed background checks on controversial NT Administrator David Connolly.",
      "time": "2026-04-26 08:45",
      "type": "news",
      "title_en": "FOI documents show vetting process for NT's controversial Crown representative",
      "title_zh": "信息自由文件显示了北领地有争议的皇家代表的审查过程",
      "description_en": "Months before a furore over his social media posts, documents show the federal government completed background checks on controversial NT Administrator David Connolly.",
      "description_zh": "在他的社交媒体帖子引起轩然大波之前几个月，文件显示联邦政府完成了对有争议的北领地行政长官大卫·康诺利的背景调查。"
    },
    {
      "title": "Police shoot at car amid chaotic night across Melbourne",
      "url": "https://www.abc.net.au/news/2026-04-26/police-investigate-drive-by-shooting-firebombing-chapel-street/106607528",
      "description": "Police are investigating multiple incidents overnight including a drive-by shooting, suspected firebombing and an allegedly violent attack on a tram.",
      "time": "2026-04-26 08:44",
      "type": "news",
      "title_en": "Police shoot at car amid chaotic night across Melbourne",
      "title_zh": "墨尔本混乱的夜晚，警察向汽车开枪",
      "description_en": "Police are investigating multiple incidents overnight including a drive-by shooting, suspected firebombing and an allegedly violent attack on a tram.",
      "description_zh": "警方正在连夜调查多起事件，包括驾车枪击事件、疑似燃烧弹事件以及据称对电车的暴力袭击事件。"
    },
    {
      "title": "How Indonesian farmers are protecting Australia's $1b citrus industry",
      "url": "https://www.abc.net.au/news/2026-04-26/australia-indonesia-project-stop-citrus-disease-spread/106563932",
      "description": "An Australian-funded project is educating Indonesian farmers about a devastating citrus disease that has spread to all major growing regions except Australia.",
      "time": "2026-04-26 08:33",
      "type": "news",
      "title_en": "How Indonesian farmers are protecting Australia's $1b citrus industry",
      "title_zh": "印度尼西亚农民如何保护澳大利亚价值十亿美元的柑橘产业",
      "description_en": "An Australian-funded project is educating Indonesian farmers about a devastating citrus disease that has spread to all major growing regions except Australia.",
      "description_zh": "澳大利亚资助的一个项目正在对印度尼西亚农民进行有关一种毁灭性柑橘病害的教育，这种病害已蔓延到除澳大利亚以外的所有主要种植区。"
    },
    {
      "title": "'Waiting for Armageddon': Nimbin preppers ready if world goes up in smoke",
      "url": "https://www.abc.net.au/news/2026-04-26/australia-preppers-are-ready-for-the-fuel-crisis/106597748",
      "description": "It may not be the end of the world, but these Australians are finding creative ways to beat the cost-of-living crisis and improve their food security in troubled times.",
      "time": "2026-04-26 08:30",
      "type": "news",
      "title_en": "'Waiting for Armageddon': Nimbin preppers ready if world goes up in smoke",
      "title_zh": "“等待世界末日”：如果世界陷入硝烟，宁宾已做好准备",
      "description_en": "It may not be the end of the world, but these Australians are finding creative ways to beat the cost-of-living crisis and improve their food security in troubled times.",
      "description_zh": "这可能不是世界末日，但这些澳大利亚人正在寻找创造性的方法来应对生活成本危机，并在困难时期改善粮食安全。"
    }
  ]
}